udt4py.cpython-39-x86_64-linux-gnu.so
udt4py_ng-1.0.0.dist-info/LICENSE
udt4py_ng-1.0.0.dist-info/WHEEL
udt4py_ng-1.0.0.dist-info/top_level.txt
udt4py_ng-1.0.0.dist-info/RECORD
udt4py_ng-1.0.0.dist-info/METADATA
udt4py_ng.libs/libudt-d7abd312.so.0
