Metadata-Version: 2.1
Name: udt4py-ng
Version: 1.0.0
Summary: libudt4 Python wrapper written with Cython
Home-page: https://github.com/wbarnha/udt4py-ng
Download-URL: https://github.com/wbarnha/udt4py-ng
Author: Samsung Electronics Co.,Ltd.
Author-email: "Samsung Electronics Co.,Ltd." <v.markovtsev@samsung.com>
Maintainer: William Barnhart
Maintainer-email: William Barnhart <williambbarnhart@gmail.com>
License: Copyright (c) 2014, Samsung Electronics Co.,Ltd.
Project-URL: Source, https://github.com/wbarnha/udt4py-ng
Project-URL: Changes, https://github.com/wbarnha/udt4py-ng/releases
Keywords: udt,pyudt,udt4,udt4py
Classifier: Development Status :: 4 - Beta
Classifier: Environment :: Console
Classifier: Intended Audience :: Developers
Classifier: License :: OSI Approved :: BSD License
Classifier: Operating System :: POSIX
Classifier: Programming Language :: Cython
Classifier: Programming Language :: Python
Classifier: Programming Language :: Python :: 3 :: Only
Classifier: Programming Language :: Python :: 3.8
Classifier: Programming Language :: Python :: 3.9
Classifier: Programming Language :: Python :: 3.10
Classifier: Programming Language :: Python :: 3.11
Classifier: Programming Language :: Python :: 3.12
Classifier: Topic :: Software Development :: Libraries
Classifier: Topic :: System :: Networking
Classifier: Operating System :: POSIX
Classifier: Operating System :: POSIX :: Linux
Requires-Python: >=3.8
License-File: LICENSE
